csv_similarity/__init__.py
csv_similarity/similarity.py
csv_similarity/__pycache__/__init__.cpython-39.pyc
csv_similarity/__pycache__/similarity.cpython-39.pyc
csv_similarity-0.0.1a0.dist-info/LICENSE
csv_similarity-0.0.1a0.dist-info/METADATA
csv_similarity-0.0.1a0.dist-info/WHEEL
csv_similarity-0.0.1a0.dist-info/entry_points.txt
csv_similarity-0.0.1a0.dist-info/top_level.txt
csv_similarity-0.0.1a0.dist-info/RECORD
